CHANGELOG
LICENSE
MANIFEST.in
README.md
setup.py
PyWechatAPI.egg-info/PKG-INFO
PyWechatAPI.egg-info/SOURCES.txt
PyWechatAPI.egg-info/dependency_links.txt
PyWechatAPI.egg-info/requires.txt
PyWechatAPI.egg-info/top_level.txt
wechat/__init__.py
wechat/accounts.py
wechat/base.py
wechat/client.py
wechat/media.py
wechat/oauth2.py
wechat/summary.py
wechat/users.py