Metadata-Version: 1.1
Name: PyWechatAPI
Version: 0.0.5
Summary: WeChat Develop Python API
Home-page: https://github.com/hitakaken/PyWechatAPI.git
Author: CaoKe
Author-email: hitakaken@gmail.com
License: MIT License
